CHANGES.txt
README.rst
setup.py
corejet/__init__.py
corejet.pivotal.egg-info/PKG-INFO
corejet.pivotal.egg-info/SOURCES.txt
corejet.pivotal.egg-info/dependency_links.txt
corejet.pivotal.egg-info/entry_points.txt
corejet.pivotal.egg-info/namespace_packages.txt
corejet.pivotal.egg-info/not-zip-safe
corejet.pivotal.egg-info/requires.txt
corejet.pivotal.egg-info/top_level.txt
corejet/pivotal/__init__.py
corejet/pivotal/config.py
corejet/pivotal/tool.py