Metadata-Version: 1.0
Name: corejet.pivotal
Version: 1.2.0
Summary: Pivotal Tracker data source for corejet.testrunner
Home-page: https://github.com/datakurre/corejet.pivotal/
Author: Asko Soukka
Author-email: asko.soukka@iki.fi
License: GPL
Keywords: corejet pivotal
Platform: UNKNOWN
Classifier: Programming Language :: Python
